pyoccur/__init__.py
pyoccur/pyoccur.py
pyoccur-0.1.0.dist-info/WHEEL
pyoccur-0.1.0.dist-info/METADATA
pyoccur-0.1.0.dist-info/RECORD
