Metadata-Version: 2.1
Name: pyoccur
Version: 0.1.0
Summary: Operations with duplicates in python lists
Home-page: https://github.com/amrs-tech/pyoccur/
Author: amrs-tech
Author-email: amrs.tech@gmail.com
Requires-Python: >=3.7,<4.0
Classifier: Programming Language :: Python :: 3
Classifier: Programming Language :: Python :: 3.10
Classifier: Programming Language :: Python :: 3.7
Classifier: Programming Language :: Python :: 3.8
Classifier: Programming Language :: Python :: 3.9
Project-URL: Repository, https://github.com/amrs-tech/pyoccur/
